{"id":"google/cloud/speech/credentials","name":"Credentials","title":["Google","Cloud","Speech","Credentials"],"description":"<h1 id=\"credentials\">Credentials</h1>\n\n<p>Represents the authentication and authorization used to connect to the\nSpeech API.</p>","source":"google-cloud-speech/lib/google/cloud/speech/credentials.rb#L40","resources":[],"examples":[{"caption":"","code":"require \"google/cloud/speech\"\n\nkeyfile = \"/path/to/keyfile.json\"\ncreds = Google::Cloud::Speech::Credentials.new keyfile\n\nspeech = Google::Cloud::Speech.new(\n  project_id: \"my-project\",\n  credentials: creds\n)\n\nspeech.project_id #=> \"my-project\""}],"methods":[]}