{"id":"google/privacy/dlp/v2beta1/imagelocation","name":"ImageLocation","title":["Google","Privacy","Dlp","V2beta1","ImageLocation"],"description":"<p>Bounding box encompassing detected text within an image.</p>","source":"google-cloud-dlp/lib/google/cloud/dlp/v2beta1/doc/google/privacy/dlp/v2beta1/dlp.rb#L188","resources":[],"examples":[],"methods":[{"id":"top-instance","type":"instance","name":"top","title":["Google","Privacy","Dlp","V2beta1","ImageLocation#top"],"description":"","source":"google-cloud-dlp/lib/google/cloud/dlp/v2beta1/doc/google/privacy/dlp/v2beta1/dlp.rb#L188","resources":[],"examples":[],"params":[],"exceptions":[],"returns":[{"types":["Integer"],"description":"Top coordinate of the bounding box. (0,0) is upper left."}]},{"id":"top=-instance","type":"instance","name":"top=","title":["Google","Privacy","Dlp","V2beta1","ImageLocation#top="],"description":"","source":"google-cloud-dlp/lib/google/cloud/dlp/v2beta1/doc/google/privacy/dlp/v2beta1/dlp.rb#L188","resources":[],"examples":[],"params":[],"exceptions":[],"returns":[{"types":["Integer"],"description":"Top coordinate of the bounding box. (0,0) is upper left."}]},{"id":"left-instance","type":"instance","name":"left","title":["Google","Privacy","Dlp","V2beta1","ImageLocation#left"],"description":"","source":"google-cloud-dlp/lib/google/cloud/dlp/v2beta1/doc/google/privacy/dlp/v2beta1/dlp.rb#L188","resources":[],"examples":[],"params":[],"exceptions":[],"returns":[{"types":["Integer"],"description":"Left coordinate of the bounding box. (0,0) is upper left."}]},{"id":"left=-instance","type":"instance","name":"left=","title":["Google","Privacy","Dlp","V2beta1","ImageLocation#left="],"description":"","source":"google-cloud-dlp/lib/google/cloud/dlp/v2beta1/doc/google/privacy/dlp/v2beta1/dlp.rb#L188","resources":[],"examples":[],"params":[],"exceptions":[],"returns":[{"types":["Integer"],"description":"Left coordinate of the bounding box. (0,0) is upper left."}]},{"id":"width-instance","type":"instance","name":"width","title":["Google","Privacy","Dlp","V2beta1","ImageLocation#width"],"description":"","source":"google-cloud-dlp/lib/google/cloud/dlp/v2beta1/doc/google/privacy/dlp/v2beta1/dlp.rb#L188","resources":[],"examples":[],"params":[],"exceptions":[],"returns":[{"types":["Integer"],"description":"Width of the bounding box in pixels."}]},{"id":"width=-instance","type":"instance","name":"width=","title":["Google","Privacy","Dlp","V2beta1","ImageLocation#width="],"description":"","source":"google-cloud-dlp/lib/google/cloud/dlp/v2beta1/doc/google/privacy/dlp/v2beta1/dlp.rb#L188","resources":[],"examples":[],"params":[],"exceptions":[],"returns":[{"types":["Integer"],"description":"Width of the bounding box in pixels."}]},{"id":"height-instance","type":"instance","name":"height","title":["Google","Privacy","Dlp","V2beta1","ImageLocation#height"],"description":"","source":"google-cloud-dlp/lib/google/cloud/dlp/v2beta1/doc/google/privacy/dlp/v2beta1/dlp.rb#L188","resources":[],"examples":[],"params":[],"exceptions":[],"returns":[{"types":["Integer"],"description":"Height of the bounding box in pixels."}]},{"id":"height=-instance","type":"instance","name":"height=","title":["Google","Privacy","Dlp","V2beta1","ImageLocation#height="],"description":"","source":"google-cloud-dlp/lib/google/cloud/dlp/v2beta1/doc/google/privacy/dlp/v2beta1/dlp.rb#L188","resources":[],"examples":[],"params":[],"exceptions":[],"returns":[{"types":["Integer"],"description":"Height of the bounding box in pixels."}]}]}