{
  "schema": "1.0",
  "comment": "This file maps proto services/RPCs to the corresponding library clients/methods",
  "language": "ruby",
  "protoPackage": "google.shopping.merchant.reports.v1beta",
  "libraryPackage": "::Google::Shopping::Merchant::Reports::V1beta",
  "services": {
    "ReportService": {
      "clients": {
        "grpc": {
          "libraryClient": "::Google::Shopping::Merchant::Reports::V1beta::ReportService::Client",
          "rpcs": {
            "Search": {
              "methods": [
                "search"
              ]
            }
          }
        }
      }
    }
  }
}
