{
  "client_library": {
    "name": "google-cloud-datastore-admin-v1",
    "version": "0.7.0",
    "language": "RUBY",
    "apis": [
      {
        "id": "google.datastore.admin.v1",
        "version": "v1"
      }
    ]
  },
  "snippets": [
    {
      "region_tag": "datastore_v1_generated_DatastoreAdmin_ExportEntities_sync",
      "title": "Snippet for export_entities in DatastoreAdmin",
      "description": "Basic snippet for export_entities in DatastoreAdmin",
      "file": "datastore_admin/export_entities.rb",
      "language": "RUBY",
      "client_method": {
        "short_name": "export_entities",
        "full_name": "::Google::Cloud::Datastore::Admin::V1::DatastoreAdmin::Client#export_entities",
        "async": false,
        "parameters": [
          {
            "type": "::Google::Cloud::Datastore::Admin::V1::ExportEntitiesRequest",
            "name": "request"
          }
        ],
        "result_type": "::Google::Longrunning::Operation",
        "client": {
          "short_name": "DatastoreAdmin::Client",
          "full_name": "::Google::Cloud::Datastore::Admin::V1::DatastoreAdmin::Client"
        },
        "method": {
          "short_name": "ExportEntities",
          "full_name": "google.datastore.admin.v1.DatastoreAdmin.ExportEntities",
          "service": {
            "short_name": "DatastoreAdmin",
            "full_name": "google.datastore.admin.v1.DatastoreAdmin"
          }
        }
      },
      "canonical": true,
      "origin": "API_DEFINITION",
      "segments": [
        {
          "start": 20,
          "end": 39,
          "type": "FULL"
        }
      ]
    },
    {
      "region_tag": "datastore_v1_generated_DatastoreAdmin_ImportEntities_sync",
      "title": "Snippet for import_entities in DatastoreAdmin",
      "description": "Basic snippet for import_entities in DatastoreAdmin",
      "file": "datastore_admin/import_entities.rb",
      "language": "RUBY",
      "client_method": {
        "short_name": "import_entities",
        "full_name": "::Google::Cloud::Datastore::Admin::V1::DatastoreAdmin::Client#import_entities",
        "async": false,
        "parameters": [
          {
            "type": "::Google::Cloud::Datastore::Admin::V1::ImportEntitiesRequest",
            "name": "request"
          }
        ],
        "result_type": "::Google::Longrunning::Operation",
        "client": {
          "short_name": "DatastoreAdmin::Client",
          "full_name": "::Google::Cloud::Datastore::Admin::V1::DatastoreAdmin::Client"
        },
        "method": {
          "short_name": "ImportEntities",
          "full_name": "google.datastore.admin.v1.DatastoreAdmin.ImportEntities",
          "service": {
            "short_name": "DatastoreAdmin",
            "full_name": "google.datastore.admin.v1.DatastoreAdmin"
          }
        }
      },
      "canonical": true,
      "origin": "API_DEFINITION",
      "segments": [
        {
          "start": 20,
          "end": 39,
          "type": "FULL"
        }
      ]
    },
    {
      "region_tag": "datastore_v1_generated_DatastoreAdmin_CreateIndex_sync",
      "title": "Snippet for create_index in DatastoreAdmin",
      "description": "Basic snippet for create_index in DatastoreAdmin",
      "file": "datastore_admin/create_index.rb",
      "language": "RUBY",
      "client_method": {
        "short_name": "create_index",
        "full_name": "::Google::Cloud::Datastore::Admin::V1::DatastoreAdmin::Client#create_index",
        "async": false,
        "parameters": [
          {
            "type": "::Google::Cloud::Datastore::Admin::V1::CreateIndexRequest",
            "name": "request"
          }
        ],
        "result_type": "::Google::Longrunning::Operation",
        "client": {
          "short_name": "DatastoreAdmin::Client",
          "full_name": "::Google::Cloud::Datastore::Admin::V1::DatastoreAdmin::Client"
        },
        "method": {
          "short_name": "CreateIndex",
          "full_name": "google.datastore.admin.v1.DatastoreAdmin.CreateIndex",
          "service": {
            "short_name": "DatastoreAdmin",
            "full_name": "google.datastore.admin.v1.DatastoreAdmin"
          }
        }
      },
      "canonical": true,
      "origin": "API_DEFINITION",
      "segments": [
        {
          "start": 20,
          "end": 39,
          "type": "FULL"
        }
      ]
    },
    {
      "region_tag": "datastore_v1_generated_DatastoreAdmin_DeleteIndex_sync",
      "title": "Snippet for delete_index in DatastoreAdmin",
      "description": "Basic snippet for delete_index in DatastoreAdmin",
      "file": "datastore_admin/delete_index.rb",
      "language": "RUBY",
      "client_method": {
        "short_name": "delete_index",
        "full_name": "::Google::Cloud::Datastore::Admin::V1::DatastoreAdmin::Client#delete_index",
        "async": false,
        "parameters": [
          {
            "type": "::Google::Cloud::Datastore::Admin::V1::DeleteIndexRequest",
            "name": "request"
          }
        ],
        "result_type": "::Google::Longrunning::Operation",
        "client": {
          "short_name": "DatastoreAdmin::Client",
          "full_name": "::Google::Cloud::Datastore::Admin::V1::DatastoreAdmin::Client"
        },
        "method": {
          "short_name": "DeleteIndex",
          "full_name": "google.datastore.admin.v1.DatastoreAdmin.DeleteIndex",
          "service": {
            "short_name": "DatastoreAdmin",
            "full_name": "google.datastore.admin.v1.DatastoreAdmin"
          }
        }
      },
      "canonical": true,
      "origin": "API_DEFINITION",
      "segments": [
        {
          "start": 20,
          "end": 39,
          "type": "FULL"
        }
      ]
    },
    {
      "region_tag": "datastore_v1_generated_DatastoreAdmin_GetIndex_sync",
      "title": "Snippet for get_index in DatastoreAdmin",
      "description": "Basic snippet for get_index in DatastoreAdmin",
      "file": "datastore_admin/get_index.rb",
      "language": "RUBY",
      "client_method": {
        "short_name": "get_index",
        "full_name": "::Google::Cloud::Datastore::Admin::V1::DatastoreAdmin::Client#get_index",
        "async": false,
        "parameters": [
          {
            "type": "::Google::Cloud::Datastore::Admin::V1::GetIndexRequest",
            "name": "request"
          }
        ],
        "result_type": "::Google::Cloud::Datastore::Admin::V1::Index",
        "client": {
          "short_name": "DatastoreAdmin::Client",
          "full_name": "::Google::Cloud::Datastore::Admin::V1::DatastoreAdmin::Client"
        },
        "method": {
          "short_name": "GetIndex",
          "full_name": "google.datastore.admin.v1.DatastoreAdmin.GetIndex",
          "service": {
            "short_name": "DatastoreAdmin",
            "full_name": "google.datastore.admin.v1.DatastoreAdmin"
          }
        }
      },
      "canonical": true,
      "origin": "API_DEFINITION",
      "segments": [
        {
          "start": 20,
          "end": 32,
          "type": "FULL"
        }
      ]
    },
    {
      "region_tag": "datastore_v1_generated_DatastoreAdmin_ListIndexes_sync",
      "title": "Snippet for list_indexes in DatastoreAdmin",
      "description": "Basic snippet for list_indexes in DatastoreAdmin",
      "file": "datastore_admin/list_indexes.rb",
      "language": "RUBY",
      "client_method": {
        "short_name": "list_indexes",
        "full_name": "::Google::Cloud::Datastore::Admin::V1::DatastoreAdmin::Client#list_indexes",
        "async": false,
        "parameters": [
          {
            "type": "::Google::Cloud::Datastore::Admin::V1::ListIndexesRequest",
            "name": "request"
          }
        ],
        "result_type": "::Google::Cloud::Datastore::Admin::V1::ListIndexesResponse",
        "client": {
          "short_name": "DatastoreAdmin::Client",
          "full_name": "::Google::Cloud::Datastore::Admin::V1::DatastoreAdmin::Client"
        },
        "method": {
          "short_name": "ListIndexes",
          "full_name": "google.datastore.admin.v1.DatastoreAdmin.ListIndexes",
          "service": {
            "short_name": "DatastoreAdmin",
            "full_name": "google.datastore.admin.v1.DatastoreAdmin"
          }
        }
      },
      "canonical": true,
      "origin": "API_DEFINITION",
      "segments": [
        {
          "start": 20,
          "end": 38,
          "type": "FULL"
        }
      ]
    }
  ]
}