{
    "api_id": "monitoring.googleapis.com",
    "api_shortname": "monitoring",
    "client_documentation": "https://cloud.google.com/ruby/docs/reference/google-cloud-monitoring-v3/latest",
    "distribution_name": "google-cloud-monitoring-v3",
    "is_cloud": true,
    "language": "ruby",
    "name": "monitoring",
    "name_pretty": "Cloud Monitoring V3 API",
    "product_documentation": "https://cloud.google.com/monitoring",
    "release_level": "unreleased",
    "repo": "googleapis/google-cloud-ruby",
    "requires_billing": true,
    "ruby-cloud-description": "Cloud Monitoring collects metrics, events, and metadata from Google Cloud, Amazon Web Services (AWS), hosted uptime probes, and application instrumentation. Note that google-cloud-monitoring-v3 is a version-specific client library. For most uses, we recommend installing the main client library google-cloud-monitoring instead. See the readme for more details.",
    "ruby-cloud-env-prefix": "MONITORING",
    "ruby-cloud-product-url": "https://cloud.google.com/monitoring",
    "library_type": "GAPIC_AUTO"
}
