{
    "api_id": "servicemanagement.googleapis.com",
    "api_shortname": "servicemanagement",
    "client_documentation": "https://cloud.google.com/ruby/docs/reference/google-cloud-service_management-v1/latest",
    "distribution_name": "google-cloud-service_management-v1",
    "language": "ruby",
    "name": "servicemanagement",
    "name_pretty": "Service Management API V1 API",
    "product_documentation": "https://cloud.google.com/service-infrastructure/docs/overview/",
    "release_level": "preview",
    "repo": "googleapis/google-cloud-ruby",
    "requires_billing": true,
    "ruby-cloud-description": "Google Service Management allows service producers to publish their services on Google Cloud Platform so that they can be discovered and used by service consumers. Note that google-cloud-service_management-v1 is a version-specific client library. For most uses, we recommend installing the main client library google-cloud-service_management instead. See the readme for more details.",
    "ruby-cloud-env-prefix": "SERVICE_MANAGEMENT",
    "ruby-cloud-product-url": "https://cloud.google.com/service-infrastructure/docs/overview/",
    "library_type": "GAPIC_AUTO"
}
