{"id":"google/cloud/vision/v1/vertex","name":"Vertex","title":["Google","Cloud","Vision","V1","Vertex"],"description":"<p>A vertex represents a 2D point in the image.\nNOTE: the vertex coordinates are in the same scale as the original image.</p>","source":"google-cloud-vision/lib/google/cloud/vision/v1/doc/google/cloud/vision/v1/geometry.rb#L27","resources":[],"examples":[],"methods":[{"id":"x-instance","type":"instance","name":"x","title":["Google","Cloud","Vision","V1","Vertex#x"],"description":"","source":"google-cloud-vision/lib/google/cloud/vision/v1/doc/google/cloud/vision/v1/geometry.rb#L27","resources":[],"examples":[],"params":[],"exceptions":[],"returns":[{"types":["Integer"],"description":"X coordinate."}]},{"id":"x=-instance","type":"instance","name":"x=","title":["Google","Cloud","Vision","V1","Vertex#x="],"description":"","source":"google-cloud-vision/lib/google/cloud/vision/v1/doc/google/cloud/vision/v1/geometry.rb#L27","resources":[],"examples":[],"params":[],"exceptions":[],"returns":[{"types":["Integer"],"description":"X coordinate."}]},{"id":"y-instance","type":"instance","name":"y","title":["Google","Cloud","Vision","V1","Vertex#y"],"description":"","source":"google-cloud-vision/lib/google/cloud/vision/v1/doc/google/cloud/vision/v1/geometry.rb#L27","resources":[],"examples":[],"params":[],"exceptions":[],"returns":[{"types":["Integer"],"description":"Y coordinate."}]},{"id":"y=-instance","type":"instance","name":"y=","title":["Google","Cloud","Vision","V1","Vertex#y="],"description":"","source":"google-cloud-vision/lib/google/cloud/vision/v1/doc/google/cloud/vision/v1/geometry.rb#L27","resources":[],"examples":[],"params":[],"exceptions":[],"returns":[{"types":["Integer"],"description":"Y coordinate."}]}]}