{
  "schema": "1.0",
  "comment": "This file maps proto services/RPCs to the corresponding library clients/methods",
  "language": "ruby",
  "protoPackage": "google.cloud.functions.v1",
  "libraryPackage": "::Google::Cloud::Functions::V1",
  "services": {
    "CloudFunctionsService": {
      "clients": {
        "grpc": {
          "libraryClient": "::Google::Cloud::Functions::V1::CloudFunctionsService::Client",
          "rpcs": {
            "ListFunctions": {
              "methods": [
                "list_functions"
              ]
            },
            "GetFunction": {
              "methods": [
                "get_function"
              ]
            },
            "CreateFunction": {
              "methods": [
                "create_function"
              ]
            },
            "UpdateFunction": {
              "methods": [
                "update_function"
              ]
            },
            "DeleteFunction": {
              "methods": [
                "delete_function"
              ]
            },
            "CallFunction": {
              "methods": [
                "call_function"
              ]
            },
            "GenerateUploadUrl": {
              "methods": [
                "generate_upload_url"
              ]
            },
            "GenerateDownloadUrl": {
              "methods": [
                "generate_download_url"
              ]
            },
            "SetIamPolicy": {
              "methods": [
                "set_iam_policy"
              ]
            },
            "GetIamPolicy": {
              "methods": [
                "get_iam_policy"
              ]
            },
            "TestIamPermissions": {
              "methods": [
                "test_iam_permissions"
              ]
            }
          }
        }
      }
    }
  }
}
