{"id":"google/firestore/v1beta1/existencefilter","name":"ExistenceFilter","title":["Google","Firestore","V1beta1","ExistenceFilter"],"description":"<p>A digest of all the documents that match a given target.</p>","source":"google-cloud-firestore/lib/google/cloud/firestore/v1beta1/doc/google/firestore/v1beta1/write.rb#L166","resources":[],"examples":[],"methods":[{"id":"target_id-instance","type":"instance","name":"target_id","title":["Google","Firestore","V1beta1","ExistenceFilter#target_id"],"description":"","source":"google-cloud-firestore/lib/google/cloud/firestore/v1beta1/doc/google/firestore/v1beta1/write.rb#L166","resources":[],"examples":[],"params":[],"exceptions":[],"returns":[{"types":["Integer"],"description":"The target ID to which this filter applies."}]},{"id":"target_id=-instance","type":"instance","name":"target_id=","title":["Google","Firestore","V1beta1","ExistenceFilter#target_id="],"description":"","source":"google-cloud-firestore/lib/google/cloud/firestore/v1beta1/doc/google/firestore/v1beta1/write.rb#L166","resources":[],"examples":[],"params":[],"exceptions":[],"returns":[{"types":["Integer"],"description":"The target ID to which this filter applies."}]},{"id":"count-instance","type":"instance","name":"count","title":["Google","Firestore","V1beta1","ExistenceFilter#count"],"description":"","source":"google-cloud-firestore/lib/google/cloud/firestore/v1beta1/doc/google/firestore/v1beta1/write.rb#L166","resources":[],"examples":[],"params":[],"exceptions":[],"returns":[{"types":["Integer"],"description":"The total count of documents that match Google::Firestore::V1beta1::ExistenceFilter#target_id.</p>\n\n<p>If different from the count of documents in the client that match, the\nclient must manually determine which documents no longer match the target."}]},{"id":"count=-instance","type":"instance","name":"count=","title":["Google","Firestore","V1beta1","ExistenceFilter#count="],"description":"","source":"google-cloud-firestore/lib/google/cloud/firestore/v1beta1/doc/google/firestore/v1beta1/write.rb#L166","resources":[],"examples":[],"params":[],"exceptions":[],"returns":[{"types":["Integer"],"description":"The total count of documents that match Google::Firestore::V1beta1::ExistenceFilter#target_id.</p>\n\n<p>If different from the count of documents in the client that match, the\nclient must manually determine which documents no longer match the target."}]}]}