{"id":"gcloud/datastore/properties","name":"Properties","title":["Gcloud","Datastore","Properties"],"description":"<h1 id=\"properties\">Properties</h1>\n\n<p>Hash-like data structure for Datastore properties.</p>\n\n<p>See <a data-custom-type=\"gcloud/datastore/entity\" data-method=\"properties-instance\">Entity#properties</a></p>","source":"lib/gcloud/datastore/properties.rb#L26","resources":[],"examples":[],"methods":[{"id":"initialize-constructor","type":"constructor","name":"initialize","title":["Gcloud","Datastore","Properties#initialize"],"description":"","source":"lib/gcloud/datastore/properties.rb#L27","resources":[],"examples":[],"params":[],"exceptions":[],"returns":[{"types":["<a data-custom-type=\"gcloud/datastore/properties\">Properties</a>"],"description":"a new instance of Properties"}]},{"id":"[]-instance","type":"instance","name":"[]","title":["Gcloud","Datastore","Properties#[]"],"description":"","source":"lib/gcloud/datastore/properties.rb#L36","resources":[],"examples":[],"params":[],"exceptions":[],"returns":[]},{"id":"[]=-instance","type":"instance","name":"[]=","title":["Gcloud","Datastore","Properties#[]="],"description":"","source":"lib/gcloud/datastore/properties.rb#L42","resources":[],"examples":[],"params":[],"exceptions":[],"returns":[]},{"id":"exist?-instance","type":"instance","name":"exist?","title":["Gcloud","Datastore","Properties#exist?"],"description":"","source":"lib/gcloud/datastore/properties.rb#L49","resources":[],"examples":[],"params":[],"exceptions":[],"returns":[{"types":["Boolean"],"description":""}]},{"id":"fetch-instance","type":"instance","name":"fetch","title":["Gcloud","Datastore","Properties#fetch"],"description":"","source":"lib/gcloud/datastore/properties.rb#L54","resources":[],"examples":[],"params":[],"exceptions":[],"returns":[]},{"id":"each-instance","type":"instance","name":"each","title":["Gcloud","Datastore","Properties#each"],"description":"","source":"lib/gcloud/datastore/properties.rb#L60","resources":[],"examples":[],"params":[],"exceptions":[],"returns":[]},{"id":"delete-instance","type":"instance","name":"delete","title":["Gcloud","Datastore","Properties#delete"],"description":"","source":"lib/gcloud/datastore/properties.rb#L64","resources":[],"examples":[],"params":[],"exceptions":[],"returns":[]},{"id":"to_h-instance","type":"instance","name":"to_h","title":["Gcloud","Datastore","Properties#to_h"],"description":"","source":"lib/gcloud/datastore/properties.rb#L69","resources":[],"examples":[],"params":[],"exceptions":[],"returns":[]},{"id":"to_grpc-instance","type":"instance","name":"to_grpc","title":["Gcloud","Datastore","Properties#to_grpc"],"description":"","source":"lib/gcloud/datastore/properties.rb#L74","resources":[],"examples":[],"params":[],"exceptions":[],"returns":[]},{"id":"from_grpc-class","type":"class","name":"from_grpc","title":["Gcloud","Datastore","Properties.from_grpc"],"description":"","source":"lib/gcloud/datastore/properties.rb#L78","resources":[],"examples":[],"params":[],"exceptions":[],"returns":[]}]}