{
    "api_id": "parallelstore.googleapis.com",
    "api_shortname": "parallelstore",
    "client_documentation": "https://cloud.google.com/ruby/docs/reference/google-cloud-parallelstore-v1/latest",
    "distribution_name": "google-cloud-parallelstore-v1",
    "is_cloud": true,
    "language": "ruby",
    "name": "parallelstore",
    "name_pretty": "Parallelstore V1 API",
    "product_documentation": "https://cloud.google.com/parallelstore?hl=en",
    "release_level": "unreleased",
    "repo": "googleapis/google-cloud-ruby",
    "requires_billing": true,
    "ruby-cloud-description": "google-cloud-parallelstore-v1 is the official client library for the Parallelstore V1 API. Note that google-cloud-parallelstore-v1 is a version-specific client library. For most uses, we recommend installing the main client library google-cloud-parallelstore instead. See the readme for more details.",
    "ruby-cloud-product-url": "https://cloud.google.com/parallelstore?hl=en",
    "library_type": "GAPIC_AUTO"
}
